cncd_package/QC.py
cncd_package/__init__.py
cncd_package-0.1.3.dist-info/METADATA
cncd_package-0.1.3.dist-info/WHEEL
cncd_package-0.1.3.dist-info/top_level.txt
cncd_package-0.1.3.dist-info/RECORD
