Metadata-Version: 2.1
Name: cncd_package
Version: 0.1.3
Summary: A Python package for CNCD
Home-page: https://github.com/shahzaib-raza/cncd
Author: Shahzaib Raza
Author-email: shahzaib.raza@cncd.org
License: BSD 2-clause
Classifier: Development Status :: 1 - Planning
Classifier: Intended Audience :: Science/Research
Classifier: License :: OSI Approved :: BSD License
Classifier: Operating System :: POSIX :: Linux
Classifier: Programming Language :: Python :: 3.9
Classifier: Programming Language :: Python :: 3.10
Classifier: Programming Language :: Python :: 3.11
Classifier: Programming Language :: Python :: 3.12
Requires-Dist: numpy >=1.24.1
Requires-Dist: pandas >=1.5.3
